plover_plugins_manager/__init__.py
plover_plugins_manager/__main__.py
plover_plugins_manager/global_registry.py
plover_plugins_manager/local_registry.py
plover_plugins_manager/package_index.py
plover_plugins_manager/pip_wrapper.py
plover_plugins_manager/plugin_metadata.py
plover_plugins_manager/registry.py
plover_plugins_manager/requests.py
plover_plugins_manager/utils.py
plover_plugins_manager/gui_qt/__init__.py
plover_plugins_manager/gui_qt/console_widget.py
plover_plugins_manager/gui_qt/console_widget_ui.py
plover_plugins_manager/gui_qt/info_browser.py
plover_plugins_manager/gui_qt/manager.py
plover_plugins_manager/gui_qt/manager_ui.py
plover_plugins_manager/gui_qt/resources_rc.py
plover_plugins_manager/gui_qt/run_dialog.py
plover_plugins_manager/gui_qt/run_dialog_ui.py
plover_plugins_manager-0.7.9.dist-info/METADATA
plover_plugins_manager-0.7.9.dist-info/WHEEL
plover_plugins_manager-0.7.9.dist-info/entry_points.txt
plover_plugins_manager-0.7.9.dist-info/top_level.txt
plover_plugins_manager-0.7.9.dist-info/zip-safe
plover_plugins_manager-0.7.9.dist-info/RECORD
