Metadata-Version: 2.4
Name: plover_plugins_manager
Version: 0.7.9
Summary: Plugins manager for Plover
Home-page: https://github.com/benoit-pierre/plover_plugins_manager
Author: Benoit Pierre
Author-email: benoit.pierre@gmail.com
License: GNU General Public License v2 or later (GPLv2+)
Project-URL: Source Code, https://github.com/benoit-pierre/plover_plugins_manager
Project-URL: Issue Tracker, https://github.com/benoit-pierre/plover_plugins_manager/issues
Keywords: plover plover_plugin
Classifier: Development Status :: 4 - Beta
Classifier: Environment :: Plugins
Classifier: Intended Audience :: End Users/Desktop
Classifier: License :: OSI Approved :: GNU General Public License v2 or later (GPLv2+)
Classifier: Operating System :: OS Independent
Classifier: Programming Language :: Python :: 3
Classifier: Programming Language :: Python :: 3.6
Classifier: Programming Language :: Python :: 3.7
Classifier: Programming Language :: Python :: 3.8
Classifier: Programming Language :: Python :: 3.9
Classifier: Programming Language :: Python :: 3.10
Requires-Python: >=3.6
Requires-Dist: pip
Requires-Dist: pkginfo>=1.4.2
Requires-Dist: plover[gui_qt]>=4.0.0.dev8
Requires-Dist: pygments
Requires-Dist: readme-renderer[md]
Requires-Dist: requests>=2.0.0
Requires-Dist: requests-cache>=0.4.11
Requires-Dist: requests-futures>=0.9.8
Requires-Dist: setuptools
Requires-Dist: wheel
Provides-Extra: test
Requires-Dist: pytest; extra == "test"
Requires-Dist: pytest-shutil; extra == "test"
